{
  "id": "c_major_scale",
  "title": "The C Major Scale",
  "description": "The foundation of Western harmony. Learn the specific pattern of whole and half steps that builds a Major scale.",
  "sessions": [
    {
      "id": "whole_half_pattern",
      "title": "The Magic Formula",
      "description": "Learn the W-W-H-W-W-W-H pattern of a major scale.",
      "version": 1
    },
    {
      "id": "scale_degrees",
      "title": "Scale Degrees",
      "description": "Learn how the notes of a scale are numbered 1 through 8.",
      "version": 1
    }
  ],
  "proficiencies": [
    {
      "id": "prof_c_major_scale_mastery",
      "title": "Mastery of The C Major Scale",
      "description": "Capability specific to mod_c_major_scale.",
      "levels": [
        {
          "id": "prof_c_major_scale_lvl0",
          "index": 0,
          "description": "Baseline Proficiency",
          "criteria": "Knows the formula W-W-H-W-W-W-H and can construct C Major."
        }
      ]
    }
  ],
  "references": []
}